psystate/__init__.py
psystate/controller.py
psystate/events.py
psystate/states.py
psystate/stimuli.py
psystate/utils.py
psystate/stubs/__init__.pyi
psystate/stubs/controller.pyi
psystate/stubs/events.pyi
psystate/stubs/states.pyi
psystate/stubs/stimuli.pyi
psystate/stubs/utils.pyi
psystate/tests/fixtures.py
psystate/tests/integration/test_controller.py
psystate/tests/integration/test_flicker_state.py
psystate/tests/unit/test_states.py
psystate/tests/unit/test_stimuli.py
psystate-0.1.1.dist-info/LICENSE
psystate-0.1.1.dist-info/METADATA
psystate-0.1.1.dist-info/WHEEL
psystate-0.1.1.dist-info/top_level.txt
psystate-0.1.1.dist-info/RECORD
