Metadata-Version: 2.1
Name: psystate
Version: 0.1.1
Summary: Stateful experiments using Psychopy
Requires-Python: >=3.10
License-File: LICENSE
Requires-Dist: attridict
Requires-Dist: frozendict
Requires-Dist: numpy
Requires-Dist: pandas
Requires-Dist: psychopy>=2023.1.0
Requires-Dist: lazy-loader
Requires-Dist: psyquartz
Provides-Extra: dev
Requires-Dist: pytest; extra == "dev"
Requires-Dist: pytest-mock; extra == "dev"
Requires-Dist: pytest-cov; extra == "dev"
